dublib/Core.py
dublib/WebRequestor.py
dublib/CLI/Terminalyzer.py
dublib/CLI/readline.py
dublib/CLI/Templates/Bus.py
dublib/CLI/Templates/__init__.py
dublib/CLI/TextStyler/Codes.py
dublib/CLI/TextStyler/Escapes.py
dublib/CLI/TextStyler/FastStyler.py
dublib/CLI/TextStyler/__init__.py
dublib/Engine/Bus.py
dublib/Engine/Configurator.py
dublib/Engine/GetText.py
dublib/Engine/Patcher.py
dublib/Exceptions/CLI.py
dublib/Exceptions/TelebotUtils.py
dublib/Exceptions/WebRequestor.py
dublib/Exceptions/__init__.py
dublib/Methods/Data.py
dublib/Methods/Decorators.py
dublib/Methods/Filesystem.py
dublib/Methods/System.py
dublib/Polyglot/HTML.py
dublib/Polyglot/Markdown.py
dublib/Polyglot/__init__.py
dublib/TelebotUtils/Cache.py
dublib/TelebotUtils/Users.py
dublib/TelebotUtils/__init__.py
dublib/TelebotUtils/Master/Decorators.py
dublib/TelebotUtils/Master/__init__.py
dublib-0.24.3.dist-info/licenses/LICENSE
dublib-0.24.3.dist-info/METADATA
dublib-0.24.3.dist-info/WHEEL
dublib-0.24.3.dist-info/top_level.txt
dublib-0.24.3.dist-info/RECORD
