Metadata-Version: 2.4
Name: dublib
Version: 0.24.3
Summary: Коллекция полезных модулей от DUB1401.
Author-email: DUB1401 <vlad.milosta@outlook.com>
License: This is free and unencumbered software released into the public domain.
Project-URL: Documentation, https://github.com/DUB1401/dublib/tree/main/docs
Project-URL: Source Code, https://github.com/DUB1401/dublib
Project-URL: Bug Tracker, https://github.com/DUB1401/dublib/issues
Project-URL: Changelog, https://github.com/DUB1401/dublib/releases
Classifier: Development Status :: 4 - Beta
Classifier: License :: OSI Approved :: The Unlicense (Unlicense)
Classifier: Natural Language :: Russian
Classifier: Operating System :: OS Independent
Classifier: Programming Language :: Python
Classifier: Programming Language :: Python :: 3.10
Classifier: Programming Language :: Python :: 3.11
Classifier: Programming Language :: Python :: 3.12
Classifier: Programming Language :: Python :: 3.13
Classifier: Programming Language :: Python :: 3.14
Requires-Python: >=3.10
License-File: LICENSE
Requires-Dist: curl_cffi>=0.11.0
Requires-Dist: dateparser
Requires-Dist: fake-useragent>=2.0.3
Requires-Dist: httpx
Requires-Dist: httpx[http2]
Requires-Dist: orjson
Requires-Dist: prettytable
Requires-Dist: requests
Requires-Dist: pyyaml
Requires-Dist: pydantic
Requires-Dist: watchfiles
Requires-Dist: gnureadline>=8.3.3; sys_platform == "linux"
Requires-Dist: pyreadline3; sys_platform == "win32"
Provides-Extra: telebot
Requires-Dist: APScheduler; extra == "telebot"
Requires-Dist: more-itertools; extra == "telebot"
Requires-Dist: pyTelegramBotAPI; extra == "telebot"
Provides-Extra: dev
Requires-Dist: pytest; extra == "dev"
Requires-Dist: Sphinx; extra == "dev"
Requires-Dist: sphinx-rtd-theme; extra == "dev"
Requires-Dist: tomli; python_version == "3.10" and extra == "dev"
Dynamic: license-file
